LICENSE
MANIFEST.in
README.md
README.rst
VERSION
setup.cfg
setup.py
django_searchable_select.egg-info/PKG-INFO
django_searchable_select.egg-info/SOURCES.txt
django_searchable_select.egg-info/dependency_links.txt
django_searchable_select.egg-info/not-zip-safe
django_searchable_select.egg-info/requires.txt
django_searchable_select.egg-info/top_level.txt
searchableselect/__init__.py
searchableselect/__init__.pyc
searchableselect/urls.py
searchableselect/urls.pyc
searchableselect/views.py
searchableselect/views.pyc
searchableselect/widgets.py
searchableselect/widgets.pyc
searchableselect/static/searchableselect/bloodhound.min.js
searchableselect/static/searchableselect/jquery-2.2.4.min.js
searchableselect/static/searchableselect/main.css
searchableselect/static/searchableselect/main.js
searchableselect/static/searchableselect/typeahead.jquery.min.js
searchableselect/templates/searchableselect/select.html