Metadata-Version: 1.1
Name: django-searchable-select
Version: 1.4.3
Summary: django-searchable-select - a better and faster multiple selection widget with suggestions for Django
Home-page: https://github.com/and3rson/django-searchable-select
Author: Andrew Dunai
Author-email: andrew@dun.ai
License: GPLv2
Keywords: django,admin,suit,select,multiple,faster,choice
Platform: UNKNOWN
Classifier: Development Status :: 5 - Production/Stable
Classifier: Environment :: Web Environment
Classifier: Framework :: Django
Classifier: Intended Audience :: Developers
Classifier: License :: OSI Approved :: BSD License
Classifier: Operating System :: OS Independent
Classifier: Programming Language :: Python
